Classfile /C:/Users/kmcguire/Desktop/backup_extracted/minecraft/nemmie/std3.1.2tekkit/mods/EE2ServerV1.4.6.5-bukkit-mcpc-1.2.5-r5/ee/ItemRedPickaxe.class
  Last modified Jun 27, 2012; size 9403 bytes
  MD5 checksum 34a33674093923c64035dfd0f454cbfa
  Compiled from "ItemRedPickaxe.java"
public class ee.ItemRedPickaxe extends ee.ItemRedTool
  SourceFile: "ItemRedPickaxe.java"
  minor version: 0
  major version: 50
  flags: ACC_PUBLIC, ACC_SUPER
Constant pool:
    #1 = Class              #2            //  ee/ItemRedPickaxe
    #2 = Utf8               ee/ItemRedPickaxe
    #3 = Class              #4            //  ee/ItemRedTool
    #4 = Utf8               ee/ItemRedTool
    #5 = Utf8               blocksEffectiveAgainst
    #6 = Utf8               [Lnet/minecraft/server/Block;
    #7 = Utf8               <clinit>
    #8 = Utf8               ()V
    #9 = Utf8               Code
   #10 = Class              #11           //  net/minecraft/server/Block
   #11 = Utf8               net/minecraft/server/Block
   #12 = Fieldref           #10.#13       //  net/minecraft/server/Block.COBBLESTONE:Lnet/minecraft/server/Block;
   #13 = NameAndType        #14:#15       //  COBBLESTONE:Lnet/minecraft/server/Block;
   #14 = Utf8               COBBLESTONE
   #15 = Utf8               Lnet/minecraft/server/Block;
   #16 = Fieldref           #10.#17       //  net/minecraft/server/Block.DOUBLE_STEP:Lnet/minecraft/server/Block;
   #17 = NameAndType        #18:#15       //  DOUBLE_STEP:Lnet/minecraft/server/Block;
   #18 = Utf8               DOUBLE_STEP
   #19 = Fieldref           #10.#20       //  net/minecraft/server/Block.STEP:Lnet/minecraft/server/Block;
   #20 = NameAndType        #21:#15       //  STEP:Lnet/minecraft/server/Block;
   #21 = Utf8               STEP
   #22 = Fieldref           #10.#23       //  net/minecraft/server/Block.STONE:Lnet/minecraft/server/Block;
   #23 = NameAndType        #24:#15       //  STONE:Lnet/minecraft/server/Block;
   #24 = Utf8               STONE
   #25 = Fieldref           #10.#26       //  net/minecraft/server/Block.SANDSTONE:Lnet/minecraft/server/Block;
   #26 = NameAndType        #27:#15       //  SANDSTONE:Lnet/minecraft/server/Block;
   #27 = Utf8               SANDSTONE
   #28 = Fieldref           #10.#29       //  net/minecraft/server/Block.MOSSY_COBBLESTONE:Lnet/minecraft/server/Block;
   #29 = NameAndType        #30:#15       //  MOSSY_COBBLESTONE:Lnet/minecraft/server/Block;
   #30 = Utf8               MOSSY_COBBLESTONE
   #31 = Fieldref           #10.#32       //  net/minecraft/server/Block.IRON_ORE:Lnet/minecraft/server/Block;
   #32 = NameAndType        #33:#15       //  IRON_ORE:Lnet/minecraft/server/Block;
   #33 = Utf8               IRON_ORE
   #34 = Fieldref           #10.#35       //  net/minecraft/server/Block.IRON_BLOCK:Lnet/minecraft/server/Block;
   #35 = NameAndType        #36:#15       //  IRON_BLOCK:Lnet/minecraft/server/Block;
   #36 = Utf8               IRON_BLOCK
   #37 = Fieldref           #10.#38       //  net/minecraft/server/Block.COAL_ORE:Lnet/minecraft/server/Block;
   #38 = NameAndType        #39:#15       //  COAL_ORE:Lnet/minecraft/server/Block;
   #39 = Utf8               COAL_ORE
   #40 = Fieldref           #10.#41       //  net/minecraft/server/Block.GOLD_BLOCK:Lnet/minecraft/server/Block;
   #41 = NameAndType        #42:#15       //  GOLD_BLOCK:Lnet/minecraft/server/Block;
   #42 = Utf8               GOLD_BLOCK
   #43 = Fieldref           #10.#44       //  net/minecraft/server/Block.GOLD_ORE:Lnet/minecraft/server/Block;
   #44 = NameAndType        #45:#15       //  GOLD_ORE:Lnet/minecraft/server/Block;
   #45 = Utf8               GOLD_ORE
   #46 = Fieldref           #10.#47       //  net/minecraft/server/Block.DIAMOND_ORE:Lnet/minecraft/server/Block;
   #47 = NameAndType        #48:#15       //  DIAMOND_ORE:Lnet/minecraft/server/Block;
   #48 = Utf8               DIAMOND_ORE
   #49 = Fieldref           #10.#50       //  net/minecraft/server/Block.DIAMOND_BLOCK:Lnet/minecraft/server/Block;
   #50 = NameAndType        #51:#15       //  DIAMOND_BLOCK:Lnet/minecraft/server/Block;
   #51 = Utf8               DIAMOND_BLOCK
   #52 = Fieldref           #10.#53       //  net/minecraft/server/Block.REDSTONE_ORE:Lnet/minecraft/server/Block;
   #53 = NameAndType        #54:#15       //  REDSTONE_ORE:Lnet/minecraft/server/Block;
   #54 = Utf8               REDSTONE_ORE
   #55 = Fieldref           #10.#56       //  net/minecraft/server/Block.GLOWING_REDSTONE_ORE:Lnet/minecraft/server/Block;
   #56 = NameAndType        #57:#15       //  GLOWING_REDSTONE_ORE:Lnet/minecraft/server/Block;
   #57 = Utf8               GLOWING_REDSTONE_ORE
   #58 = Fieldref           #10.#59       //  net/minecraft/server/Block.ICE:Lnet/minecraft/server/Block;
   #59 = NameAndType        #60:#15       //  ICE:Lnet/minecraft/server/Block;
   #60 = Utf8               ICE
   #61 = Fieldref           #10.#62       //  net/minecraft/server/Block.NETHERRACK:Lnet/minecraft/server/Block;
   #62 = NameAndType        #63:#15       //  NETHERRACK:Lnet/minecraft/server/Block;
   #63 = Utf8               NETHERRACK
   #64 = Fieldref           #10.#65       //  net/minecraft/server/Block.LAPIS_ORE:Lnet/minecraft/server/Block;
   #65 = NameAndType        #66:#15       //  LAPIS_ORE:Lnet/minecraft/server/Block;
   #66 = Utf8               LAPIS_ORE
   #67 = Fieldref           #10.#68       //  net/minecraft/server/Block.LAPIS_BLOCK:Lnet/minecraft/server/Block;
   #68 = NameAndType        #69:#15       //  LAPIS_BLOCK:Lnet/minecraft/server/Block;
   #69 = Utf8               LAPIS_BLOCK
   #70 = Fieldref           #10.#71       //  net/minecraft/server/Block.OBSIDIAN:Lnet/minecraft/server/Block;
   #71 = NameAndType        #72:#15       //  OBSIDIAN:Lnet/minecraft/server/Block;
   #72 = Utf8               OBSIDIAN
   #73 = Fieldref           #1.#74        //  ee/ItemRedPickaxe.blocksEffectiveAgainst:[Lnet/minecraft/server/Block;
   #74 = NameAndType        #5:#6         //  blocksEffectiveAgainst:[Lnet/minecraft/server/Block;
   #75 = Utf8               LineNumberTable
   #76 = Utf8               LocalVariableTable
   #77 = Utf8               <init>
   #78 = Utf8               (I)V
   #79 = Methodref          #3.#80        //  ee/ItemRedTool."<init>":(III[Lnet/minecraft/server/Block;)V
   #80 = NameAndType        #77:#81       //  "<init>":(III[Lnet/minecraft/server/Block;)V
   #81 = Utf8               (III[Lnet/minecraft/server/Block;)V
   #82 = Utf8               this
   #83 = Utf8               Lee/ItemRedPickaxe;
   #84 = Utf8               var1
   #85 = Utf8               I
   #86 = Utf8               getStrVsBlock
   #87 = Utf8               (Lnet/minecraft/server/ItemStack;Lnet/minecraft/server/Block;I)F
   #88 = Fieldref           #10.#89       //  net/minecraft/server/Block.id:I
   #89 = NameAndType        #90:#85       //  id:I
   #90 = Utf8               id
   #91 = Fieldref           #92.#94       //  ee/EEBlock.eePedestal:Lee/BlockEEPedestal;
   #92 = Class              #93           //  ee/EEBlock
   #93 = Utf8               ee/EEBlock
   #94 = NameAndType        #95:#96       //  eePedestal:Lee/BlockEEPedestal;
   #95 = Utf8               eePedestal
   #96 = Utf8               Lee/BlockEEPedestal;
   #97 = Fieldref           #98.#89       //  ee/BlockEEPedestal.id:I
   #98 = Class              #99           //  ee/BlockEEPedestal
   #99 = Utf8               ee/BlockEEPedestal
  #100 = Fieldref           #92.#101      //  ee/EEBlock.eeStone:Lee/BlockEEStone;
  #101 = NameAndType        #102:#103     //  eeStone:Lee/BlockEEStone;
  #102 = Utf8               eeStone
  #103 = Utf8               Lee/BlockEEStone;
  #104 = Fieldref           #105.#89      //  ee/BlockEEStone.id:I
  #105 = Class              #106          //  ee/BlockEEStone
  #106 = Utf8               ee/BlockEEStone
  #107 = Fieldref           #10.#108      //  net/minecraft/server/Block.material:Lnet/minecraft/server/Material;
  #108 = NameAndType        #109:#110     //  material:Lnet/minecraft/server/Material;
  #109 = Utf8               material
  #110 = Utf8               Lnet/minecraft/server/Material;
  #111 = Fieldref           #112.#114     //  net/minecraft/server/Material.STONE:Lnet/minecraft/server/Material;
  #112 = Class              #113          //  net/minecraft/server/Material
  #113 = Utf8               net/minecraft/server/Material
  #114 = NameAndType        #24:#110      //  STONE:Lnet/minecraft/server/Material;
  #115 = Fieldref           #112.#116     //  net/minecraft/server/Material.ORE:Lnet/minecraft/server/Material;
  #116 = NameAndType        #117:#110     //  ORE:Lnet/minecraft/server/Material;
  #117 = Utf8               ORE
  #118 = Methodref          #1.#119       //  ee/ItemRedPickaxe.chargeLevel:(Lnet/minecraft/server/ItemStack;)I
  #119 = NameAndType        #120:#121     //  chargeLevel:(Lnet/minecraft/server/ItemStack;)I
  #120 = Utf8               chargeLevel
  #121 = Utf8               (Lnet/minecraft/server/ItemStack;)I
  #122 = Float              16.0f
  #123 = Methodref          #3.#124       //  ee/ItemRedTool.getDestroySpeed:(Lnet/minecraft/server/ItemStack;Lnet/minecraft/server/Block;)F
  #124 = NameAndType        #125:#126     //  getDestroySpeed:(Lnet/minecraft/server/ItemStack;Lnet/minecraft/server/Block;)F
  #125 = Utf8               getDestroySpeed
  #126 = Utf8               (Lnet/minecraft/server/ItemStack;Lnet/minecraft/server/Block;)F
  #127 = Float              1200000.0f
  #128 = Utf8               Lnet/minecraft/server/ItemStack;
  #129 = Utf8               var2
  #130 = Utf8               var3
  #131 = Utf8               var4
  #132 = Utf8               F
  #133 = Utf8               StackMapTable
  #134 = Utf8               a
  #135 = Utf8               (Lnet/minecraft/server/ItemStack;IIIILnet/minecraft/server/EntityLiving;)Z
  #136 = Class              #137          //  net/minecraft/server/EntityHuman
  #137 = Utf8               net/minecraft/server/EntityHuman
  #138 = Methodref          #139.#141     //  ee/EEBase.getToolMode:(Lnet/minecraft/server/EntityHuman;)I
  #139 = Class              #140          //  ee/EEBase
  #140 = Utf8               ee/EEBase
  #141 = NameAndType        #142:#143     //  getToolMode:(Lnet/minecraft/server/EntityHuman;)I
  #142 = Utf8               getToolMode
  #143 = Utf8               (Lnet/minecraft/server/EntityHuman;)I
  #144 = Fieldref           #136.#145     //  net/minecraft/server/EntityHuman.world:Lnet/minecraft/server/World;
  #145 = NameAndType        #146:#147     //  world:Lnet/minecraft/server/World;
  #146 = Utf8               world
  #147 = Utf8               Lnet/minecraft/server/World;
  #148 = Methodref          #139.#149     //  ee/EEBase.direction:(Lnet/minecraft/server/EntityHuman;)D
  #149 = NameAndType        #150:#151     //  direction:(Lnet/minecraft/server/EntityHuman;)D
  #150 = Utf8               direction
  #151 = Utf8               (Lnet/minecraft/server/EntityHuman;)D
  #152 = Methodref          #1.#153       //  ee/ItemRedPickaxe.doTallImpact:(Lnet/minecraft/server/World;Lnet/minecraft/server/ItemStack;Lnet/minecraft/server/EntityHuman;IIID)V
  #153 = NameAndType        #154:#155     //  doTallImpact:(Lnet/minecraft/server/World;Lnet/minecraft/server/ItemStack;Lnet/minecraft/server/EntityHuman;IIID)V
  #154 = Utf8               doTallImpact
  #155 = Utf8               (Lnet/minecraft/server/World;Lnet/minecraft/server/ItemStack;Lnet/minecraft/server/EntityHuman;IIID)V
  #156 = Methodref          #139.#157     //  ee/EEBase.heading:(Lnet/minecraft/server/EntityHuman;)D
  #157 = NameAndType        #158:#151     //  heading:(Lnet/minecraft/server/EntityHuman;)D
  #158 = Utf8               heading
  #159 = Methodref          #1.#160       //  ee/ItemRedPickaxe.doWideImpact:(Lnet/minecraft/server/World;Lnet/minecraft/server/ItemStack;IIID)V
  #160 = NameAndType        #161:#162     //  doWideImpact:(Lnet/minecraft/server/World;Lnet/minecraft/server/ItemStack;IIID)V
  #161 = Utf8               doWideImpact
  #162 = Utf8               (Lnet/minecraft/server/World;Lnet/minecraft/server/ItemStack;IIID)V
  #163 = Methodref          #1.#164       //  ee/ItemRedPickaxe.doLongImpact:(Lnet/minecraft/server/World;Lnet/minecraft/server/ItemStack;IIID)V
  #164 = NameAndType        #165:#162     //  doLongImpact:(Lnet/minecraft/server/World;Lnet/minecraft/server/ItemStack;IIID)V
  #165 = Utf8               doLongImpact
  #166 = Utf8               var5
  #167 = Utf8               var6
  #168 = Utf8               Lnet/minecraft/server/EntityLiving;
  #169 = Utf8               var7
  #170 = Utf8               Lnet/minecraft/server/EntityHuman;
  #171 = Methodref          #1.#172       //  ee/ItemRedPickaxe.cleanDroplist:(Lnet/minecraft/server/ItemStack;)V
  #172 = NameAndType        #173:#174     //  cleanDroplist:(Lnet/minecraft/server/ItemStack;)V
  #173 = Utf8               cleanDroplist
  #174 = Utf8               (Lnet/minecraft/server/ItemStack;)V
  #175 = Double             2.0d
  #177 = Double             3.0d
  #179 = Double             4.0d
  #181 = Double             5.0d
  #183 = Methodref          #184.#186     //  net/minecraft/server/World.getTypeId:(III)I
  #184 = Class              #185          //  net/minecraft/server/World
  #185 = Utf8               net/minecraft/server/World
  #186 = NameAndType        #187:#188     //  getTypeId:(III)I
  #187 = Utf8               getTypeId
  #188 = Utf8               (III)I
  #189 = Methodref          #184.#190     //  net/minecraft/server/World.getData:(III)I
  #190 = NameAndType        #191:#188     //  getData:(III)I
  #191 = Utf8               getData
  #192 = Methodref          #1.#193       //  ee/ItemRedPickaxe.canBreak:(II)Z
  #193 = NameAndType        #194:#195     //  canBreak:(II)Z
  #194 = Utf8               canBreak
  #195 = Utf8               (II)Z
  #196 = Methodref          #1.#197       //  ee/ItemRedPickaxe.scanBlockAndBreak:(Lnet/minecraft/server/World;Lnet/minecraft/server/ItemStack;III)V
  #197 = NameAndType        #198:#199     //  scanBlockAndBreak:(Lnet/minecraft/server/World;Lnet/minecraft/server/ItemStack;III)V
  #198 = Utf8               scanBlockAndBreak
  #199 = Utf8               (Lnet/minecraft/server/World;Lnet/minecraft/server/ItemStack;III)V
  #200 = Double             0.5d
  #202 = Methodref          #1.#203       //  ee/ItemRedPickaxe.ejectDropList:(Lnet/minecraft/server/World;Lnet/minecraft/server/ItemStack;DDD)V
  #203 = NameAndType        #204:#205     //  ejectDropList:(Lnet/minecraft/server/World;Lnet/minecraft/server/ItemStack;DDD)V
  #204 = Utf8               ejectDropList
  #205 = Utf8               (Lnet/minecraft/server/World;Lnet/minecraft/server/ItemStack;DDD)V
  #206 = Utf8               D
  #207 = Utf8               var8
  #208 = Utf8               var9
  #209 = Utf8               var10
  #210 = Utf8               var11
  #211 = Utf8               var12
  #212 = Utf8               var13
  #213 = Utf8               var14
  #214 = Utf8               doBreak
  #215 = Utf8               (Lnet/minecraft/server/ItemStack;Lnet/minecraft/server/World;Lnet/minecraft/server/EntityHuman;)V
  #216 = Methodref          #139.#217     //  ee/EEBase.playerX:(Lnet/minecraft/server/EntityHuman;)D
  #217 = NameAndType        #218:#151     //  playerX:(Lnet/minecraft/server/EntityHuman;)D
  #218 = Utf8               playerX
  #219 = Methodref          #139.#220     //  ee/EEBase.playerY:(Lnet/minecraft/server/EntityHuman;)D
  #220 = NameAndType        #221:#151     //  playerY:(Lnet/minecraft/server/EntityHuman;)D
  #221 = Utf8               playerY
  #222 = Methodref          #139.#223     //  ee/EEBase.playerZ:(Lnet/minecraft/server/EntityHuman;)D
  #223 = NameAndType        #224:#151     //  playerZ:(Lnet/minecraft/server/EntityHuman;)D
  #224 = Utf8               playerZ
  #225 = Methodref          #1.#226       //  ee/ItemRedPickaxe.isOre:(I)Z
  #226 = NameAndType        #227:#228     //  isOre:(I)Z
  #227 = Utf8               isOre
  #228 = Utf8               (I)Z
  #229 = Methodref          #1.#230       //  ee/ItemRedPickaxe.startSearch:(Lnet/minecraft/server/World;Lnet/minecraft/server/ItemStack;Lnet/minecraft/server/EntityHuman;IIIIZ)V
  #230 = NameAndType        #231:#232     //  startSearch:(Lnet/minecraft/server/World;Lnet/minecraft/server/ItemStack;Lnet/minecraft/server/EntityHuman;IIIIZ)V
  #231 = Utf8               startSearch
  #232 = Utf8               (Lnet/minecraft/server/World;Lnet/minecraft/server/ItemStack;Lnet/minecraft/server/EntityHuman;IIIIZ)V
  #233 = Class              #234          //  net/minecraft/server/ItemStack
  #234 = Utf8               net/minecraft/server/ItemStack
  #235 = Fieldref           #10.#236      //  net/minecraft/server/Block.byId:[Lnet/minecraft/server/Block;
  #236 = NameAndType        #237:#6       //  byId:[Lnet/minecraft/server/Block;
  #237 = Utf8               byId
  #238 = Methodref          #10.#239      //  net/minecraft/server/Block.getBlockDropped:(Lnet/minecraft/server/World;IIIII)Ljava/util/ArrayList;
  #239 = NameAndType        #240:#241     //  getBlockDropped:(Lnet/minecraft/server/World;IIIII)Ljava/util/ArrayList;
  #240 = Utf8               getBlockDropped
  #241 = Utf8               (Lnet/minecraft/server/World;IIIII)Ljava/util/ArrayList;
  #242 = Methodref          #243.#245     //  java/util/ArrayList.iterator:()Ljava/util/Iterator;
  #243 = Class              #244          //  java/util/ArrayList
  #244 = Utf8               java/util/ArrayList
  #245 = NameAndType        #246:#247     //  iterator:()Ljava/util/Iterator;
  #246 = Utf8               iterator
  #247 = Utf8               ()Ljava/util/Iterator;
  #248 = InterfaceMethodref #249.#251     //  java/util/Iterator.next:()Ljava/lang/Object;
  #249 = Class              #250          //  java/util/Iterator
  #250 = Utf8               java/util/Iterator
  #251 = NameAndType        #252:#253     //  next:()Ljava/lang/Object;
  #252 = Utf8               next
  #253 = Utf8               ()Ljava/lang/Object;
  #254 = Methodref          #1.#255       //  ee/ItemRedPickaxe.addToDroplist:(Lnet/minecraft/server/ItemStack;Lnet/minecraft/server/ItemStack;)V
  #255 = NameAndType        #256:#257     //  addToDroplist:(Lnet/minecraft/server/ItemStack;Lnet/minecraft/server/ItemStack;)V
  #256 = Utf8               addToDroplist
  #257 = Utf8               (Lnet/minecraft/server/ItemStack;Lnet/minecraft/server/ItemStack;)V
  #258 = InterfaceMethodref #249.#259     //  java/util/Iterator.hasNext:()Z
  #259 = NameAndType        #260:#261     //  hasNext:()Z
  #260 = Utf8               hasNext
  #261 = Utf8               ()Z
  #262 = Methodref          #184.#263     //  net/minecraft/server/World.setTypeId:(IIII)Z
  #263 = NameAndType        #264:#265     //  setTypeId:(IIII)Z
  #264 = Utf8               setTypeId
  #265 = Utf8               (IIII)Z
  #266 = Fieldref           #184.#267     //  net/minecraft/server/World.random:Ljava/util/Random;
  #267 = NameAndType        #268:#269     //  random:Ljava/util/Random;
  #268 = Utf8               random
  #269 = Utf8               Ljava/util/Random;
  #270 = Methodref          #271.#273     //  java/util/Random.nextInt:(I)I
  #271 = Class              #272          //  java/util/Random
  #272 = Utf8               java/util/Random
  #273 = NameAndType        #274:#275     //  nextInt:(I)I
  #274 = Utf8               nextInt
  #275 = Utf8               (I)I
  #276 = String             #277          //  largesmoke
  #277 = Utf8               largesmoke
  #278 = Methodref          #184.#279     //  net/minecraft/server/World.a:(Ljava/lang/String;DDDDDD)V
  #279 = NameAndType        #134:#280     //  a:(Ljava/lang/String;DDDDDD)V
  #280 = Utf8               (Ljava/lang/String;DDDDDD)V
  #281 = String             #282          //  explode
  #282 = Utf8               explode
  #283 = Utf8               Ljava/util/ArrayList;
  #284 = Utf8               Ljava/util/Iterator;
  #285 = Methodref          #10.#286      //  net/minecraft/server/Block.b:()Z
  #286 = NameAndType        #287:#261     //  b:()Z
  #287 = Utf8               b
  #288 = Methodref          #10.#289      //  net/minecraft/server/Block.hasTileEntity:(I)Z
  #289 = NameAndType        #290:#228     //  hasTileEntity:(I)Z
  #290 = Utf8               hasTileEntity
  #291 = Fieldref           #10.#292      //  net/minecraft/server/Block.BEDROCK:Lnet/minecraft/server/Block;
  #292 = NameAndType        #293:#15      //  BEDROCK:Lnet/minecraft/server/Block;
  #293 = Utf8               BEDROCK
  #294 = Methodref          #1.#295       //  ee/ItemRedPickaxe.canDestroySpecialBlock:(Lnet/minecraft/server/Block;)Z
  #295 = NameAndType        #296:#297     //  canDestroySpecialBlock:(Lnet/minecraft/server/Block;)Z
  #296 = Utf8               canDestroySpecialBlock
  #297 = Utf8               (Lnet/minecraft/server/Block;)Z
  #298 = Utf8               interactWith
  #299 = Utf8               (Lnet/minecraft/server/ItemStack;Lnet/minecraft/server/EntityHuman;Lnet/minecraft/server/World;IIII)Z
  #300 = Methodref          #301.#303     //  net/minecraft/server/EEProxy.isClient:(Lnet/minecraft/server/World;)Z
  #301 = Class              #302          //  net/minecraft/server/EEProxy
  #302 = Utf8               net/minecraft/server/EEProxy
  #303 = NameAndType        #304:#305     //  isClient:(Lnet/minecraft/server/World;)Z
  #304 = Utf8               isClient
  #305 = Utf8               (Lnet/minecraft/server/World;)Z
  #306 = Methodref          #307.#309     //  ee/EEMaps.isOreBlock:(I)Z
  #307 = Class              #308          //  ee/EEMaps
  #308 = Utf8               ee/EEMaps
  #309 = NameAndType        #310:#228     //  isOreBlock:(I)Z
  #310 = Utf8               isOreBlock
  #311 = Utf8               (Lnet/minecraft/server/ItemStack;Lnet/minecraft/server/World;Lnet/minecraft/server/EntityHuman;)Lnet/minecraft/server/ItemStack;
  #312 = Methodref          #1.#313       //  ee/ItemRedPickaxe.doBreak:(Lnet/minecraft/server/ItemStack;Lnet/minecraft/server/World;Lnet/minecraft/server/EntityHuman;)V
  #313 = NameAndType        #214:#215     //  doBreak:(Lnet/minecraft/server/ItemStack;Lnet/minecraft/server/World;Lnet/minecraft/server/EntityHuman;)V
  #314 = String             #315          //  Nice try. You can't break bedrock.
  #315 = Utf8               Nice try. You can't break bedrock.
  #316 = Methodref          #136.#317     //  net/minecraft/server/EntityHuman.a:(Ljava/lang/String;)V
  #317 = NameAndType        #134:#318     //  a:(Ljava/lang/String;)V
  #318 = Utf8               (Ljava/lang/String;)V
  #319 = String             #320          //  flash
  #320 = Utf8               flash
  #321 = Float              0.8f
  #322 = Float              1.5f
  #323 = Methodref          #184.#324     //  net/minecraft/server/World.makeSound:(Lnet/minecraft/server/Entity;Ljava/lang/String;FF)V
  #324 = NameAndType        #325:#326     //  makeSound:(Lnet/minecraft/server/Entity;Ljava/lang/String;FF)V
  #325 = Utf8               makeSound
  #326 = Utf8               (Lnet/minecraft/server/Entity;Ljava/lang/String;FF)V
  #327 = Methodref          #136.#328     //  net/minecraft/server/EntityHuman.C_:()V
  #328 = NameAndType        #329:#8       //  C_:()V
  #329 = Utf8               C_
  #330 = Methodref          #1.#331       //  ee/ItemRedPickaxe.doBreakS:(Lnet/minecraft/server/World;Lnet/minecraft/server/ItemStack;Lnet/minecraft/server/EntityHuman;IIII)V
  #331 = NameAndType        #332:#333     //  doBreakS:(Lnet/minecraft/server/World;Lnet/minecraft/server/ItemStack;Lnet/minecraft/server/EntityHuman;IIII)V
  #332 = Utf8               doBreakS
  #333 = Utf8               (Lnet/minecraft/server/World;Lnet/minecraft/server/ItemStack;Lnet/minecraft/server/EntityHuman;IIII)V
  #334 = Utf8               Z
  #335 = Utf8               doRelease
  #336 = Utf8               doAlternate
  #337 = Methodref          #139.#338     //  ee/EEBase.updateToolMode:(Lnet/minecraft/server/EntityHuman;)V
  #338 = NameAndType        #339:#340     //  updateToolMode:(Lnet/minecraft/server/EntityHuman;)V
  #339 = Utf8               updateToolMode
  #340 = Utf8               (Lnet/minecraft/server/EntityHuman;)V
  #341 = Utf8               doToggle
  #342 = Utf8               SourceFile
  #343 = Utf8               ItemRedPickaxe.java
{
  static {};
    flags: ACC_STATIC
    Code:
      stack=4, locals=0, args_size=0
         0: bipush        20
         2: anewarray     #10                 // class net/minecraft/server/Block
         5: dup           
         6: iconst_0      
         7: getstatic     #12                 // Field net/minecraft/server/Block.COBBLESTONE:Lnet/minecraft/server/Block;
        10: aastore       
        11: dup           
        12: iconst_1      
        13: getstatic     #16                 // Field net/minecraft/server/Block.DOUBLE_STEP:Lnet/minecraft/server/Block;
        16: aastore       
        17: dup           
        18: iconst_2      
        19: getstatic     #19                 // Field net/minecraft/server/Block.STEP:Lnet/minecraft/server/Block;
        22: aastore       
        23: dup           
        24: iconst_3      
        25: getstatic     #22                 // Field net/minecraft/server/Block.STONE:Lnet/minecraft/server/Block;
        28: aastore       
        29: dup           
        30: iconst_4      
        31: getstatic     #25                 // Field net/minecraft/server/Block.SANDSTONE:Lnet/minecraft/server/Block;
        34: aastore       
        35: dup           
        36: iconst_5      
        37: getstatic     #28                 // Field net/minecraft/server/Block.MOSSY_COBBLESTONE:Lnet/minecraft/server/Block;
        40: aastore       
        41: dup           
        42: bipush        6
        44: getstatic     #31                 // Field net/minecraft/server/Block.IRON_ORE:Lnet/minecraft/server/Block;
        47: aastore       
        48: dup           
        49: bipush        7
        51: getstatic     #34                 // Field net/minecraft/server/Block.IRON_BLOCK:Lnet/minecraft/server/Block;
        54: aastore       
        55: dup           
        56: bipush        8
        58: getstatic     #37                 // Field net/minecraft/server/Block.COAL_ORE:Lnet/minecraft/server/Block;
        61: aastore       
        62: dup           
        63: bipush        9
        65: getstatic     #40                 // Field net/minecraft/server/Block.GOLD_BLOCK:Lnet/minecraft/server/Block;
        68: aastore       
        69: dup           
        70: bipush        10
        72: getstatic     #43                 // Field net/minecraft/server/Block.GOLD_ORE:Lnet/minecraft/server/Block;
        75: aastore       
        76: dup           
        77: bipush        11
        79: getstatic     #46                 // Field net/minecraft/server/Block.DIAMOND_ORE:Lnet/minecraft/server/Block;
        82: aastore       
        83: dup           
        84: bipush        12
        86: getstatic     #49                 // Field net/minecraft/server/Block.DIAMOND_BLOCK:Lnet/minecraft/server/Block;
        89: aastore       
        90: dup           
        91: bipush        13
        93: getstatic     #52                 // Field net/minecraft/server/Block.REDSTONE_ORE:Lnet/minecraft/server/Block;
        96: aastore       
        97: dup           
        98: bipush        14
       100: getstatic     #55                 // Field net/minecraft/server/Block.GLOWING_REDSTONE_ORE:Lnet/minecraft/server/Block;
       103: aastore       
       104: dup           
       105: bipush        15
       107: getstatic     #58                 // Field net/minecraft/server/Block.ICE:Lnet/minecraft/server/Block;
       110: aastore       
       111: dup           
       112: bipush        16
       114: getstatic     #61                 // Field net/minecraft/server/Block.NETHERRACK:Lnet/minecraft/server/Block;
       117: aastore       
       118: dup           
       119: bipush        17
       121: getstatic     #64                 // Field net/minecraft/server/Block.LAPIS_ORE:Lnet/minecraft/server/Block;
       124: aastore       
       125: dup           
       126: bipush        18
       128: getstatic     #67                 // Field net/minecraft/server/Block.LAPIS_BLOCK:Lnet/minecraft/server/Block;
       131: aastore       
       132: dup           
       133: bipush        19
       135: getstatic     #70                 // Field net/minecraft/server/Block.OBSIDIAN:Lnet/minecraft/server/Block;
       138: aastore       
       139: putstatic     #73                 // Field blocksEffectiveAgainst:[Lnet/minecraft/server/Block;
       142: return        
      LineNumberTable:
        line 15: 0
        line 13: 142
      LocalVariableTable:
        Start  Length  Slot  Name   Signature

  protected ee.ItemRedPickaxe(int);
    flags: ACC_PROTECTED
    Code:
      stack=5, locals=2, args_size=2
         0: aload_0       
         1: iload_1       
         2: iconst_3      
         3: bipush        6
         5: getstatic     #73                 // Field blocksEffectiveAgainst:[Lnet/minecraft/server/Block;
         8: invokespecial #79                 // Method ee/ItemRedTool."<init>":(III[Lnet/minecraft/server/Block;)V
        11: return        
      LineNumberTable:
        line 19: 0
        line 20: 11
      LocalVariableTable:
        Start  Length  Slot  Name   Signature
               0      12     0  this   Lee/ItemRedPickaxe;
               0      12     1  var1   I

  public float getStrVsBlock(net.minecraft.server.ItemStack, net.minecraft.server.Block, int);
    flags: ACC_PUBLIC
    Code:
      stack=4, locals=5, args_size=4
         0: fconst_1      
         1: fstore        4
         3: aload_2       
         4: getfield      #88                 // Field net/minecraft/server/Block.id:I
         7: getstatic     #91                 // Field ee/EEBlock.eePedestal:Lee/BlockEEPedestal;
        10: getfield      #97                 // Field ee/BlockEEPedestal.id:I
        13: if_icmpne     20
        16: iload_3       
        17: ifeq          131
        20: aload_2       
        21: getfield      #88                 // Field net/minecraft/server/Block.id:I
        24: getstatic     #100                // Field ee/EEBlock.eeStone:Lee/BlockEEStone;
        27: getfield      #104                // Field ee/BlockEEStone.id:I
        30: if_icmpne     45
        33: iload_3       
        34: bipush        8
        36: if_icmpeq     131
        39: iload_3       
        40: bipush        9
        42: if_icmpeq     131
        45: aload_2       
        46: getfield      #107                // Field net/minecraft/server/Block.material:Lnet/minecraft/server/Material;
        49: getstatic     #111                // Field net/minecraft/server/Material.STONE:Lnet/minecraft/server/Material;
        52: if_acmpeq     65
        55: aload_2       
        56: getfield      #107                // Field net/minecraft/server/Block.material:Lnet/minecraft/server/Material;
        59: getstatic     #115                // Field net/minecraft/server/Material.ORE:Lnet/minecraft/server/Material;
        62: if_acmpne     91
        65: aload_0       
        66: aload_1       
        67: invokevirtual #118                // Method chargeLevel:(Lnet/minecraft/server/ItemStack;)I
        70: ifle          91
        73: ldc           #122                // float 16.0f
        75: ldc           #122                // float 16.0f
        77: aload_0       
        78: aload_1       
        79: invokevirtual #118                // Method chargeLevel:(Lnet/minecraft/server/ItemStack;)I
        82: i2f           
        83: fmul          
        84: fload         4
        86: fdiv          
        87: fadd          
        88: goto          136
        91: aload_2       
        92: getfield      #107                // Field net/minecraft/server/Block.material:Lnet/minecraft/server/Material;
        95: getstatic     #111                // Field net/minecraft/server/Material.STONE:Lnet/minecraft/server/Material;
        98: if_acmpeq     123
       101: aload_2       
       102: getfield      #107                // Field net/minecraft/server/Block.material:Lnet/minecraft/server/Material;
       105: getstatic     #115                // Field net/minecraft/server/Material.ORE:Lnet/minecraft/server/Material;
       108: if_acmpeq     123
       111: aload_0       
       112: aload_1       
       113: aload_2       
       114: invokespecial #123                // Method ee/ItemRedTool.getDestroySpeed:(Lnet/minecraft/server/ItemStack;Lnet/minecraft/server/Block;)F
       117: fload         4
       119: fdiv          
       120: goto          136
       123: ldc           #122                // float 16.0f
       125: fload         4
       127: fdiv          
       128: goto          136
       131: ldc           #127                // float 1200000.0f
       133: fload         4
       135: fdiv          
       136: freturn       
      LineNumberTable:
        line 24: 0
        line 25: 3
      LocalVariableTable:
        Start  Length  Slot  Name   Signature
               0     137     0  this   Lee/ItemRedPickaxe;
               0     137     1  var1   Lnet/minecraft/server/ItemStack;
               0     137     2  var2   Lnet/minecraft/server/Block;
               0     137     3  var3   I
               3     134     4  var4   F
      StackMapTable: number_of_entries = 8
           frame_type = 252 /* append */
             offset_delta = 20
        locals = [ float ]
           frame_type = 24 /* same */
           frame_type = 19 /* same */
           frame_type = 25 /* same */
           frame_type = 31 /* same */
           frame_type = 68 /* same_locals_1_stack_item */
          stack = [ float ]
           frame_type = 2 /* same */
           frame_type = 68 /* same_locals_1_stack_item */
          stack = [ float ]


  public boolean a(net.minecraft.server.ItemStack, int, int, int, int, net.minecraft.server.EntityLiving);
    flags: ACC_PUBLIC
    Code:
      stack=9, locals=8, args_size=7
         0: aconst_null   
         1: astore        7
         3: aload         6
         5: instanceof    #136                // class net/minecraft/server/EntityHuman
         8: ifeq          123
        11: aload         6
        13: checkcast     #136                // class net/minecraft/server/EntityHuman
        16: astore        7
        18: aload         7
        20: invokestatic  #138                // Method ee/EEBase.getToolMode:(Lnet/minecraft/server/EntityHuman;)I
        23: ifeq          121
        26: aload         7
        28: invokestatic  #138                // Method ee/EEBase.getToolMode:(Lnet/minecraft/server/EntityHuman;)I
        31: iconst_1      
        32: if_icmpne     60
        35: aload_0       
        36: aload         7
        38: getfield      #144                // Field net/minecraft/server/EntityHuman.world:Lnet/minecraft/server/World;
        41: aload_1       
        42: aload         7
        44: iload_3       
        45: iload         4
        47: iload         5
        49: aload         7
        51: invokestatic  #148                // Method ee/EEBase.direction:(Lnet/minecraft/server/EntityHuman;)D
        54: invokevirtual #152                // Method doTallImpact:(Lnet/minecraft/server/World;Lnet/minecraft/server/ItemStack;Lnet/minecraft/server/EntityHuman;IIID)V
        57: goto          121
        60: aload         7
        62: invokestatic  #138                // Method ee/EEBase.getToolMode:(Lnet/minecraft/server/EntityHuman;)I
        65: iconst_2      
        66: if_icmpne     92
        69: aload_0       
        70: aload         7
        72: getfield      #144                // Field net/minecraft/server/EntityHuman.world:Lnet/minecraft/server/World;
        75: aload_1       
        76: iload_3       
        77: iload         4
        79: iload         5
        81: aload         7
        83: invokestatic  #156                // Method ee/EEBase.heading:(Lnet/minecraft/server/EntityHuman;)D
        86: invokevirtual #159                // Method doWideImpact:(Lnet/minecraft/server/World;Lnet/minecraft/server/ItemStack;IIID)V
        89: goto          121
        92: aload         7
        94: invokestatic  #138                // Method ee/EEBase.getToolMode:(Lnet/minecraft/server/EntityHuman;)I
        97: iconst_3      
        98: if_icmpne     121
       101: aload_0       
       102: aload         7
       104: getfield      #144                // Field net/minecraft/server/EntityHuman.world:Lnet/minecraft/server/World;
       107: aload_1       
       108: iload_3       
       109: iload         4
       111: iload         5
       113: aload         7
       115: invokestatic  #148                // Method ee/EEBase.direction:(Lnet/minecraft/server/EntityHuman;)D
       118: invokevirtual #163                // Method doLongImpact:(Lnet/minecraft/server/World;Lnet/minecraft/server/ItemStack;IIID)V
       121: iconst_1      
       122: ireturn       
       123: iconst_1      
       124: ireturn       
      LineNumberTable:
        line 30: 0
        line 32: 3
        line 34: 11
        line 36: 18
        line 38: 26
        line 40: 35
        line 42: 60
        line 44: 69
        line 46: 92
        line 48: 101
        line 52: 121
        line 56: 123
      LocalVariableTable:
        Start  Length  Slot  Name   Signature
               0     125     0  this   Lee/ItemRedPickaxe;
               0     125     1  var1   Lnet/minecraft/server/ItemStack;
               0     125     2  var2   I
               0     125     3  var3   I
               0     125     4  var4   I
               0     125     5  var5   I
               0     125     6  var6   Lnet/minecraft/server/EntityLiving;
               3     122     7  var7   Lnet/minecraft/server/EntityHuman;
      StackMapTable: number_of_entries = 4
           frame_type = 252 /* append */
             offset_delta = 60
        locals = [ class net/minecraft/server/EntityHuman ]
           frame_type = 31 /* same */
           frame_type = 28 /* same */
           frame_type = 1 /* same */


  public void doLongImpact(net.minecraft.server.World, net.minecraft.server.ItemStack, int, int, int, double);
    flags: ACC_PUBLIC
    Code:
      stack=9, locals=14, args_size=7
         0: aload_0       
         1: aload_2       
         2: invokevirtual #171                // Method cleanDroplist:(Lnet/minecraft/server/ItemStack;)V
         5: iconst_1      
         6: istore        8
         8: goto          163
        11: iload_3       
        12: istore        9
        14: iload         4
        16: istore        10
        18: iload         5
        20: istore        11
        22: dload         6
        24: dconst_0      
        25: dcmpl         
        26: ifne          36
        29: iload         4
        31: iload         8
        33: isub          
        34: istore        10
        36: dload         6
        38: dconst_1      
        39: dcmpl         
        40: ifne          50
        43: iload         10
        45: iload         8
        47: iadd          
        48: istore        10
        50: dload         6
        52: ldc2_w        #175                // double 2.0d
        55: dcmpl         
        56: ifne          66
        59: iload         5
        61: iload         8
        63: iadd          
        64: istore        11
        66: dload         6
        68: ldc2_w        #177                // double 3.0d
        71: dcmpl         
        72: ifne          81
        75: iload_3       
        76: iload         8
        78: isub          
        79: istore        9
        81: dload         6
        83: ldc2_w        #179                // double 4.0d
        86: dcmpl         
        87: ifne          97
        90: iload         11
        92: iload         8
        94: isub          
        95: istore        11
        97: dload         6
        99: ldc2_w        #181                // double 5.0d
       102: dcmpl         
       103: ifne          113
       106: iload         9
       108: iload         8
       110: iadd          
       111: istore        9
       113: aload_1       
       114: iload         9
       116: iload         10
       118: iload         11
       120: invokevirtual #183                // Method net/minecraft/server/World.getTypeId:(III)I
       123: istore        12
       125: aload_1       
       126: iload         9
       128: iload         10
       130: iload         11
       132: invokevirtual #189                // Method net/minecraft/server/World.getData:(III)I
       135: istore        13
       137: aload_0       
       138: iload         12
       140: iload         13
       142: invokevirtual #192                // Method canBreak:(II)Z
       145: ifeq          160
       148: aload_0       
       149: aload_1       
       150: aload_2       
       151: iload         9
       153: iload         10
       155: iload         11
       157: invokevirtual #196                // Method scanBlockAndBreak:(Lnet/minecraft/server/World;Lnet/minecraft/server/ItemStack;III)V
       160: iinc          8, 1
       163: iload         8
       165: iconst_2      
       166: if_icmple     11
       169: aload_0       
       170: aload_1       
       171: aload_2       
       172: iload_3       
       173: i2d           
       174: iload         4
       176: i2d           
       177: ldc2_w        #200                // double 0.5d
       180: dadd          
       181: iload         5
       183: i2d           
       184: invokevirtual #202                // Method ejectDropList:(Lnet/minecraft/server/World;Lnet/minecraft/server/ItemStack;DDD)V
       187: return        
      LineNumberTable:
        line 62: 0
        line 64: 5
        line 66: 11
        line 67: 14
        line 68: 18
        line 70: 22
        line 72: 29
        line 75: 36
        line 77: 43
        line 80: 50
        line 82: 59
        line 85: 66
        line 87: 75
        line 90: 81
        line 92: 90
        line 95: 97
        line 97: 106
        line 100: 113
        line 101: 125
        line 103: 137
        line 105: 148
        line 64: 160
        line 109: 169
        line 110: 187
      LocalVariableTable:
        Start  Length  Slot  Name   Signature
               0     188     0  this   Lee/ItemRedPickaxe;
               0     188     1  var1   Lnet/minecraft/server/World;
               0     188     2  var2   Lnet/minecraft/server/ItemStack;
               0     188     3  var3   I
               0     188     4  var4   I
               0     188     5  var5   I
               0     188     6  var6   D
               8     161     8  var8   I
              14     146     9  var9   I
              18     142    10 var10   I
              22     138    11 var11   I
             125      35    12 var12   I
             137      23    13 var13   I
      StackMapTable: number_of_entries = 9
           frame_type = 252 /* append */
             offset_delta = 11
        locals = [ int ]
           frame_type = 254 /* append */
             offset_delta = 24
        locals = [ int, int, int ]
           frame_type = 13 /* same */
           frame_type = 15 /* same */
           frame_type = 14 /* same */
           frame_type = 15 /* same */
           frame_type = 15 /* same */
           frame_type = 248 /* chop */
          offset_delta = 46
           frame_type = 2 /* same */


  public void doWideImpact(net.minecraft.server.World, net.minecraft.server.ItemStack, int, int, int, double);
    flags: ACC_PUBLIC
    Code:
      stack=9, locals=13, args_size=7
         0: aload_0       
         1: aload_2       
         2: invokevirtual #171                // Method cleanDroplist:(Lnet/minecraft/server/ItemStack;)V
         5: iconst_m1     
         6: istore        8
         8: goto          107
        11: iload_3       
        12: istore        9
        14: iload         5
        16: istore        10
        18: iload         8
        20: ifeq          104
        23: dload         6
        25: ldc2_w        #175                // double 2.0d
        28: dcmpl         
        29: ifeq          51
        32: dload         6
        34: ldc2_w        #179                // double 4.0d
        37: dcmpl         
        38: ifeq          51
        41: iload         5
        43: iload         8
        45: iadd          
        46: istore        10
        48: goto          57
        51: iload_3       
        52: iload         8
        54: iadd          
        55: istore        9
        57: aload_1       
        58: iload         9
        60: iload         4
        62: iload         10
        64: invokevirtual #183                // Method net/minecraft/server/World.getTypeId:(III)I
        67: istore        11
        69: aload_1       
        70: iload         9
        72: iload         4
        74: iload         10
        76: invokevirtual #189                // Method net/minecraft/server/World.getData:(III)I
        79: istore        12
        81: aload_0       
        82: iload         11
        84: iload         12
        86: invokevirtual #192                // Method canBreak:(II)Z
        89: ifeq          104
        92: aload_0       
        93: aload_1       
        94: aload_2       
        95: iload         9
        97: iload         4
        99: iload         10
       101: invokevirtual #196                // Method scanBlockAndBreak:(Lnet/minecraft/server/World;Lnet/minecraft/server/ItemStack;III)V
       104: iinc          8, 1
       107: iload         8
       109: iconst_1      
       110: if_icmple     11
       113: aload_0       
       114: aload_1       
       115: aload_2       
       116: iload_3       
       117: i2d           
       118: iload         4
       120: i2d           
       121: ldc2_w        #200                // double 0.5d
       124: dadd          
       125: iload         5
       127: i2d           
       128: invokevirtual #202                // Method ejectDropList:(Lnet/minecraft/server/World;Lnet/minecraft/server/ItemStack;DDD)V
       131: return        
      LineNumberTable:
        line 114: 0
        line 116: 5
        line 118: 11
        line 119: 14
        line 121: 18
        line 123: 23
        line 125: 41
        line 129: 51
        line 132: 57
        line 133: 69
        line 135: 81
        line 137: 92
        line 116: 104
        line 142: 113
        line 143: 131
      LocalVariableTable:
        Start  Length  Slot  Name   Signature
               0     132     0  this   Lee/ItemRedPickaxe;
               0     132     1  var1   Lnet/minecraft/server/World;
               0     132     2  var2   Lnet/minecraft/server/ItemStack;
               0     132     3  var3   I
               0     132     4  var4   I
               0     132     5  var5   I
               0     132     6  var6   D
               8     105     8  var8   I
              14      90     9  var9   I
              18      86    10 var11   I
              69      35    11 var12   I
              81      23    12 var13   I
      StackMapTable: number_of_entries = 5
           frame_type = 252 /* append */
             offset_delta = 11
        locals = [ int ]
           frame_type = 253 /* append */
             offset_delta = 39
        locals = [ int, int ]
           frame_type = 5 /* same */
           frame_type = 249 /* chop */
          offset_delta = 46
           frame_type = 2 /* same */


  public void doTallImpact(net.minecraft.server.World, net.minecraft.server.ItemStack, net.minecraft.server.EntityHuman, int, int, int, double);
    flags: ACC_PUBLIC
    Code:
      stack=9, locals=15, args_size=8
         0: aload_0       
         1: aload_2       
         2: invokevirtual #171                // Method cleanDroplist:(Lnet/minecraft/server/ItemStack;)V
         5: iconst_m1     
         6: istore        9
         8: goto          141
        11: iload         4
        13: istore        10
        15: iload         5
        17: istore        11
        19: iload         6
        21: istore        12
        23: iload         9
        25: ifeq          138
        28: dload         7
        30: dconst_0      
        31: dcmpl         
        32: ifeq          52
        35: dload         7
        37: dconst_1      
        38: dcmpl         
        39: ifeq          52
        42: iload         5
        44: iload         9
        46: iadd          
        47: istore        11
        49: goto          91
        52: aload_3       
        53: invokestatic  #156                // Method ee/EEBase.heading:(Lnet/minecraft/server/EntityHuman;)D
        56: ldc2_w        #175                // double 2.0d
        59: dcmpl         
        60: ifeq          84
        63: aload_3       
        64: invokestatic  #156                // Method ee/EEBase.heading:(Lnet/minecraft/server/EntityHuman;)D
        67: ldc2_w        #179                // double 4.0d
        70: dcmpl         
        71: ifeq          84
        74: iload         4
        76: iload         9
        78: iadd          
        79: istore        10
        81: goto          91
        84: iload         6
        86: iload         9
        88: iadd          
        89: istore        12
        91: aload_1       
        92: iload         10
        94: iload         11
        96: iload         12
        98: invokevirtual #183                // Method net/minecraft/server/World.getTypeId:(III)I
       101: istore        13
       103: aload_1       
       104: iload         10
       106: iload         11
       108: iload         12
       110: invokevirtual #189                // Method net/minecraft/server/World.getData:(III)I
       113: istore        14
       115: aload_0       
       116: iload         13
       118: iload         14
       120: invokevirtual #192                // Method canBreak:(II)Z
       123: ifeq          138
       126: aload_0       
       127: aload_1       
       128: aload_2       
       129: iload         10
       131: iload         11
       133: iload         12
       135: invokevirtual #196                // Method scanBlockAndBreak:(Lnet/minecraft/server/World;Lnet/minecraft/server/ItemStack;III)V
       138: iinc          9, 1
       141: iload         9
       143: iconst_1      
       144: if_icmple     11
       147: aload_0       
       148: aload_1       
       149: aload_2       
       150: iload         4
       152: i2d           
       153: iload         5
       155: i2d           
       156: ldc2_w        #200                // double 0.5d
       159: dadd          
       160: iload         6
       162: i2d           
       163: invokevirtual #202                // Method ejectDropList:(Lnet/minecraft/server/World;Lnet/minecraft/server/ItemStack;DDD)V
       166: return        
      LineNumberTable:
        line 147: 0
        line 149: 5
        line 151: 11
        line 152: 15
        line 153: 19
        line 155: 23
        line 157: 28
        line 159: 42
        line 161: 52
        line 163: 74
        line 167: 84
        line 170: 91
        line 171: 103
        line 173: 115
        line 175: 126
        line 149: 138
        line 180: 147
        line 181: 166
      LocalVariableTable:
        Start  Length  Slot  Name   Signature
               0     167     0  this   Lee/ItemRedPickaxe;
               0     167     1  var1   Lnet/minecraft/server/World;
               0     167     2  var2   Lnet/minecraft/server/ItemStack;
               0     167     3  var3   Lnet/minecraft/server/EntityHuman;
               0     167     4  var4   I
               0     167     5  var5   I
               0     167     6  var6   I
               0     167     7  var7   D
               8     139     9  var9   I
              15     123    10 var10   I
              19     119    11 var11   I
              23     115    12 var12   I
             103      35    13 var13   I
             115      23    14 var14   I
      StackMapTable: number_of_entries = 6
           frame_type = 252 /* append */
             offset_delta = 11
        locals = [ int ]
           frame_type = 254 /* append */
             offset_delta = 40
        locals = [ int, int, int ]
           frame_type = 31 /* same */
           frame_type = 6 /* same */
           frame_type = 248 /* chop */
          offset_delta = 46
           frame_type = 2 /* same */


  public void doBreak(net.minecraft.server.ItemStack, net.minecraft.server.World, net.minecraft.server.EntityHuman);
    flags: ACC_PUBLIC
    Code:
      stack=9, locals=11, args_size=4
         0: aload_0       
         1: aload_1       
         2: invokevirtual #118                // Method chargeLevel:(Lnet/minecraft/server/ItemStack;)I
         5: ifle          132
         8: aload_3       
         9: invokestatic  #216                // Method ee/EEBase.playerX:(Lnet/minecraft/server/EntityHuman;)D
        12: d2i           
        13: istore        4
        15: aload_3       
        16: invokestatic  #219                // Method ee/EEBase.playerY:(Lnet/minecraft/server/EntityHuman;)D
        19: d2i           
        20: istore        5
        22: aload_3       
        23: invokestatic  #222                // Method ee/EEBase.playerZ:(Lnet/minecraft/server/EntityHuman;)D
        26: d2i           
        27: istore        6
        29: bipush        -2
        31: istore        7
        33: goto          126
        36: bipush        -2
        38: istore        8
        40: goto          117
        43: bipush        -2
        45: istore        9
        47: goto          108
        50: aload_2       
        51: iload         4
        53: iload         7
        55: iadd          
        56: iload         5
        58: iload         8
        60: iadd          
        61: iload         6
        63: iload         9
        65: iadd          
        66: invokevirtual #183                // Method net/minecraft/server/World.getTypeId:(III)I
        69: istore        10
        71: aload_0       
        72: iload         10
        74: invokespecial #225                // Method isOre:(I)Z
        77: ifeq          105
        80: aload_0       
        81: aload_2       
        82: aload_1       
        83: aload_3       
        84: iload         10
        86: iload         4
        88: iload         7
        90: iadd          
        91: iload         5
        93: iload         8
        95: iadd          
        96: iload         6
        98: iload         9
       100: iadd          
       101: iconst_1      
       102: invokevirtual #229                // Method startSearch:(Lnet/minecraft/server/World;Lnet/minecraft/server/ItemStack;Lnet/minecraft/server/EntityHuman;IIIIZ)V
       105: iinc          9, 1
       108: iload         9
       110: iconst_2      
       111: if_icmple     50
       114: iinc          8, 1
       117: iload         8
       119: iconst_2      
       120: if_icmple     43
       123: iinc          7, 1
       126: iload         7
       128: iconst_2      
       129: if_icmple     36
       132: return        
      LineNumberTable:
        line 185: 0
        line 187: 8
        line 188: 15
        line 189: 22
        line 191: 29
        line 193: 36
        line 195: 43
        line 197: 50
        line 199: 71
        line 201: 80
        line 195: 105
        line 193: 114
        line 191: 123
        line 207: 132
      LocalVariableTable:
        Start  Length  Slot  Name   Signature
               0     133     0  this   Lee/ItemRedPickaxe;
               0     133     1  var1   Lnet/minecraft/server/ItemStack;
               0     133     2  var2   Lnet/minecraft/server/World;
               0     133     3  var3   Lnet/minecraft/server/EntityHuman;
              15     117     4  var4   I
              22     110     5  var5   I
              29     103     6  var6   I
              33      99     7  var7   I
              40      83     8  var8   I
              47      67     9  var9   I
              71      34    10 var10   I
      StackMapTable: number_of_entries = 8
           frame_type = 255 /* full_frame */
          offset_delta = 36
          locals = [ class ee/ItemRedPickaxe, class net/minecraft/server/ItemStack, class net/minecraft/server/World, class net/minecraft/server/EntityHuman, int, int, int, int ]
          stack = []
           frame_type = 252 /* append */
             offset_delta = 6
        locals = [ int ]
           frame_type = 252 /* append */
             offset_delta = 6
        locals = [ int ]
           frame_type = 54 /* same */
           frame_type = 2 /* same */
           frame_type = 250 /* chop */
          offset_delta = 8
           frame_type = 250 /* chop */
          offset_delta = 8
           frame_type = 255 /* full_frame */
          offset_delta = 5
          locals = [ class ee/ItemRedPickaxe, class net/minecraft/server/ItemStack, class net/minecraft/server/World, class net/minecraft/server/EntityHuman ]
          stack = []


  public void scanBlockAndBreak(net.minecraft.server.World, net.minecraft.server.ItemStack, int, int, int);
    flags: ACC_PUBLIC
    Code:
      stack=14, locals=11, args_size=6
         0: aload_1       
         1: iload_3       
         2: iload         4
         4: iload         5
         6: invokevirtual #183                // Method net/minecraft/server/World.getTypeId:(III)I
         9: istore        6
        11: aload_1       
        12: iload_3       
        13: iload         4
        15: iload         5
        17: invokevirtual #189                // Method net/minecraft/server/World.getData:(III)I
        20: istore        7
        22: getstatic     #235                // Field net/minecraft/server/Block.byId:[Lnet/minecraft/server/Block;
        25: iload         6
        27: aaload        
        28: aload_1       
        29: iload_3       
        30: iload         4
        32: iload         5
        34: iload         7
        36: iconst_0      
        37: invokevirtual #238                // Method net/minecraft/server/Block.getBlockDropped:(Lnet/minecraft/server/World;IIIII)Ljava/util/ArrayList;
        40: astore        8
        42: aload         8
        44: invokevirtual #242                // Method java/util/ArrayList.iterator:()Ljava/util/Iterator;
        47: astore        9
        49: goto          71
        52: aload         9
        54: invokeinterface #248,  1          // InterfaceMethod java/util/Iterator.next:()Ljava/lang/Object;
        59: checkcast     #233                // class net/minecraft/server/ItemStack
        62: astore        10
        64: aload_0       
        65: aload_2       
        66: aload         10
        68: invokevirtual #254                // Method addToDroplist:(Lnet/minecraft/server/ItemStack;Lnet/minecraft/server/ItemStack;)V
        71: aload         9
        73: invokeinterface #258,  1          // InterfaceMethod java/util/Iterator.hasNext:()Z
        78: ifne          52
        81: aload_1       
        82: iload_3       
        83: iload         4
        85: iload         5
        87: iconst_0      
        88: invokevirtual #262                // Method net/minecraft/server/World.setTypeId:(IIII)Z
        91: pop           
        92: aload_1       
        93: getfield      #266                // Field net/minecraft/server/World.random:Ljava/util/Random;
        96: bipush        8
        98: invokevirtual #270                // Method java/util/Random.nextInt:(I)I
       101: ifne          122
       104: aload_1       
       105: ldc_w         #276                // String largesmoke
       108: iload_3       
       109: i2d           
       110: iload         4
       112: i2d           
       113: iload         5
       115: i2d           
       116: dconst_0      
       117: dconst_0      
       118: dconst_0      
       119: invokevirtual #278                // Method net/minecraft/server/World.a:(Ljava/lang/String;DDDDDD)V
       122: aload_1       
       123: getfield      #266                // Field net/minecraft/server/World.random:Ljava/util/Random;
       126: bipush        8
       128: invokevirtual #270                // Method java/util/Random.nextInt:(I)I
       131: ifne          152
       134: aload_1       
       135: ldc_w         #281                // String explode
       138: iload_3       
       139: i2d           
       140: iload         4
       142: i2d           
       143: iload         5
       145: i2d           
       146: dconst_0      
       147: dconst_0      
       148: dconst_0      
       149: invokevirtual #278                // Method net/minecraft/server/World.a:(Ljava/lang/String;DDDDDD)V
       152: return        
      LineNumberTable:
        line 211: 0
        line 212: 11
        line 213: 22
        line 214: 42
        line 216: 49
        line 218: 52
        line 219: 64
        line 216: 71
        line 222: 81
        line 224: 92
        line 226: 104
        line 229: 122
        line 231: 134
        line 233: 152
      LocalVariableTable:
        Start  Length  Slot  Name   Signature
               0     153     0  this   Lee/ItemRedPickaxe;
               0     153     1  var1   Lnet/minecraft/server/World;
               0     153     2  var2   Lnet/minecraft/server/ItemStack;
               0     153     3  var3   I
               0     153     4  var4   I
               0     153     5  var5   I
              11     142     6  var6   I
              22     131     7  var7   I
              42     111     8  var8   Ljava/util/ArrayList;
              49     104     9  var9   Ljava/util/Iterator;
              64       7    10 var10   Lnet/minecraft/server/ItemStack;
      StackMapTable: number_of_entries = 4
           frame_type = 255 /* full_frame */
          offset_delta = 52
          locals = [ class ee/ItemRedPickaxe, class net/minecraft/server/World, class net/minecraft/server/ItemStack, int, int, int, int, int, class java/util/ArrayList, class java/util/Iterator ]
          stack = []
           frame_type = 18 /* same */
           frame_type = 50 /* same */
           frame_type = 29 /* same */


  public boolean canBreak(int, int);
    flags: ACC_PUBLIC
    Code:
      stack=3, locals=4, args_size=3
         0: getstatic     #235                // Field net/minecraft/server/Block.byId:[Lnet/minecraft/server/Block;
         3: iload_1       
         4: aaload        
         5: ifnonnull     10
         8: iconst_0      
         9: ireturn       
        10: getstatic     #235                // Field net/minecraft/server/Block.byId:[Lnet/minecraft/server/Block;
        13: iload_1       
        14: aaload        
        15: invokevirtual #285                // Method net/minecraft/server/Block.b:()Z
        18: ifne          23
        21: iconst_0      
        22: ireturn       
        23: getstatic     #235                // Field net/minecraft/server/Block.byId:[Lnet/minecraft/server/Block;
        26: iload_1       
        27: aaload        
        28: iload_2       
        29: invokevirtual #288                // Method net/minecraft/server/Block.hasTileEntity:(I)Z
        32: ifne          104
        35: iload_1       
        36: getstatic     #291                // Field net/minecraft/server/Block.BEDROCK:Lnet/minecraft/server/Block;
        39: getfield      #88                 // Field net/minecraft/server/Block.id:I
        42: if_icmpeq     104
        45: getstatic     #235                // Field net/minecraft/server/Block.byId:[Lnet/minecraft/server/Block;
        48: iload_1       
        49: aaload        
        50: getfield      #107                // Field net/minecraft/server/Block.material:Lnet/minecraft/server/Material;
        53: ifnonnull     58
        56: iconst_0      
        57: ireturn       
        58: iconst_0      
        59: istore_3      
        60: goto          80
        63: iload_1       
        64: getstatic     #73                 // Field blocksEffectiveAgainst:[Lnet/minecraft/server/Block;
        67: iload_3       
        68: aaload        
        69: getfield      #88                 // Field net/minecraft/server/Block.id:I
        72: if_icmpne     77
        75: iconst_1      
        76: ireturn       
        77: iinc          3, 1
        80: iload_3       
        81: getstatic     #73                 // Field blocksEffectiveAgainst:[Lnet/minecraft/server/Block;
        84: arraylength   
        85: if_icmplt     63
        88: aload_0       
        89: getstatic     #235                // Field net/minecraft/server/Block.byId:[Lnet/minecraft/server/Block;
        92: iload_1       
        93: aaload        
        94: invokevirtual #294                // Method canDestroySpecialBlock:(Lnet/minecraft/server/Block;)Z
        97: ifeq          102
       100: iconst_1      
       101: ireturn       
       102: iconst_0      
       103: ireturn       
       104: iconst_0      
       105: ireturn       
      LineNumberTable:
        line 237: 0
        line 239: 8
        line 241: 10
        line 243: 21
        line 245: 23
        line 247: 45
        line 249: 56
        line 253: 58
        line 255: 63
        line 257: 75
        line 253: 77
        line 261: 88
        line 263: 100
        line 267: 102
        line 273: 104
      LocalVariableTable:
        Start  Length  Slot  Name   Signature
               0     106     0  this   Lee/ItemRedPickaxe;
               0     106     1  var1   I
               0     106     2  var2   I
              60      28     3  var3   I
      StackMapTable: number_of_entries = 8
           frame_type = 10 /* same */
           frame_type = 12 /* same */
           frame_type = 34 /* same */
           frame_type = 252 /* append */
             offset_delta = 4
        locals = [ int ]
           frame_type = 13 /* same */
           frame_type = 2 /* same */
           frame_type = 250 /* chop */
          offset_delta = 21
           frame_type = 1 /* same */


  public boolean interactWith(net.minecraft.server.ItemStack, net.minecraft.server.EntityHuman, net.minecraft.server.World, int, int, int, int);
    flags: ACC_PUBLIC
    Code:
      stack=9, locals=9, args_size=8
         0: aload_3       
         1: invokestatic  #300                // Method net/minecraft/server/EEProxy.isClient:(Lnet/minecraft/server/World;)Z
         4: ifeq          9
         7: iconst_0      
         8: ireturn       
         9: aload_0       
        10: aload_1       
        11: invokevirtual #118                // Method chargeLevel:(Lnet/minecraft/server/ItemStack;)I
        14: iconst_1      
        15: if_icmplt     62
        18: aload_0       
        19: aload_1       
        20: invokevirtual #171                // Method cleanDroplist:(Lnet/minecraft/server/ItemStack;)V
        23: aload_3       
        24: iload         4
        26: iload         5
        28: iload         6
        30: invokevirtual #183                // Method net/minecraft/server/World.getTypeId:(III)I
        33: istore        8
        35: aload_0       
        36: iload         8
        38: invokespecial #225                // Method isOre:(I)Z
        41: ifeq          60
        44: aload_0       
        45: aload_3       
        46: aload_1       
        47: aload_2       
        48: iload         8
        50: iload         4
        52: iload         5
        54: iload         6
        56: iconst_0      
        57: invokevirtual #229                // Method startSearch:(Lnet/minecraft/server/World;Lnet/minecraft/server/ItemStack;Lnet/minecraft/server/EntityHuman;IIIIZ)V
        60: iconst_1      
        61: ireturn       
        62: iconst_0      
        63: ireturn       
      LineNumberTable:
        line 283: 0
        line 285: 7
        line 287: 9
        line 289: 18
        line 290: 23
        line 292: 35
        line 294: 44
        line 297: 60
        line 301: 62
      LocalVariableTable:
        Start  Length  Slot  Name   Signature
               0      64     0  this   Lee/ItemRedPickaxe;
               0      64     1  var1   Lnet/minecraft/server/ItemStack;
               0      64     2  var2   Lnet/minecraft/server/EntityHuman;
               0      64     3  var3   Lnet/minecraft/server/World;
               0      64     4  var4   I
               0      64     5  var5   I
               0      64     6  var6   I
               0      64     7  var7   I
              35      27     8  var8   I
      StackMapTable: number_of_entries = 3
           frame_type = 9 /* same */
           frame_type = 252 /* append */
             offset_delta = 50
        locals = [ int ]
           frame_type = 250 /* chop */
          offset_delta = 1


  public net.minecraft.server.ItemStack a(net.minecraft.server.ItemStack, net.minecraft.server.World, net.minecraft.server.EntityHuman);
    flags: ACC_PUBLIC
    Code:
      stack=4, locals=4, args_size=4
         0: aload_2       
         1: invokestatic  #300                // Method net/minecraft/server/EEProxy.isClient:(Lnet/minecraft/server/World;)Z
         4: ifeq          9
         7: aload_1       
         8: areturn       
         9: aload_0       
        10: aload_1       
        11: aload_2       
        12: aload_3       
        13: invokevirtual #312                // Method doBreak:(Lnet/minecraft/server/ItemStack;Lnet/minecraft/server/World;Lnet/minecraft/server/EntityHuman;)V
        16: aload_1       
        17: areturn       
      LineNumberTable:
        line 315: 0
        line 317: 7
        line 321: 9
        line 322: 16
      LocalVariableTable:
        Start  Length  Slot  Name   Signature
               0      18     0  this   Lee/ItemRedPickaxe;
               0      18     1  var1   Lnet/minecraft/server/ItemStack;
               0      18     2  var2   Lnet/minecraft/server/World;
               0      18     3  var3   Lnet/minecraft/server/EntityHuman;
      StackMapTable: number_of_entries = 1
           frame_type = 9 /* same */


  public void startSearch(net.minecraft.server.World, net.minecraft.server.ItemStack, net.minecraft.server.EntityHuman, int, int, int, int, boolean);
    flags: ACC_PUBLIC
    Code:
      stack=8, locals=9, args_size=9
         0: iload         4
         2: getstatic     #291                // Field net/minecraft/server/Block.BEDROCK:Lnet/minecraft/server/Block;
         5: getfield      #88                 // Field net/minecraft/server/Block.id:I
         8: if_icmpne     21
        11: aload_3       
        12: ldc_w         #314                // String Nice try. You can't break bedrock.
        15: invokevirtual #316                // Method net/minecraft/server/EntityHuman.a:(Ljava/lang/String;)V
        18: goto          59
        21: aload_1       
        22: aload_3       
        23: ldc_w         #319                // String flash
        26: ldc_w         #321                // float 0.8f
        29: ldc_w         #322                // float 1.5f
        32: invokevirtual #323                // Method net/minecraft/server/World.makeSound:(Lnet/minecraft/server/Entity;Ljava/lang/String;FF)V
        35: iload         8
        37: ifeq          44
        40: aload_3       
        41: invokevirtual #327                // Method net/minecraft/server/EntityHuman.C_:()V
        44: aload_0       
        45: aload_1       
        46: aload_2       
        47: aload_3       
        48: iload         4
        50: iload         5
        52: iload         6
        54: iload         7
        56: invokevirtual #330                // Method doBreakS:(Lnet/minecraft/server/World;Lnet/minecraft/server/ItemStack;Lnet/minecraft/server/EntityHuman;IIII)V
        59: return        
      LineNumberTable:
        line 328: 0
        line 330: 11
        line 334: 21
        line 336: 35
        line 338: 40
        line 341: 44
        line 343: 59
      LocalVariableTable:
        Start  Length  Slot  Name   Signature
               0      60     0  this   Lee/ItemRedPickaxe;
               0      60     1  var1   Lnet/minecraft/server/World;
               0      60     2  var2   Lnet/minecraft/server/ItemStack;
               0      60     3  var3   Lnet/minecraft/server/EntityHuman;
               0      60     4  var4   I
               0      60     5  var5   I
               0      60     6  var6   I
               0      60     7  var7   I
               0      60     8  var8   Z
      StackMapTable: number_of_entries = 3
           frame_type = 21 /* same */
           frame_type = 22 /* same */
           frame_type = 14 /* same */


  public void doBreakS(net.minecraft.server.World, net.minecraft.server.ItemStack, net.minecraft.server.EntityHuman, int, int, int, int);
    flags: ACC_PUBLIC
    Code:
      stack=9, locals=11, args_size=8
         0: aload_0       
         1: aload_1       
         2: aload_2       
         3: iload         5
         5: iload         6
         7: iload         7
         9: invokevirtual #196                // Method scanBlockAndBreak:(Lnet/minecraft/server/World;Lnet/minecraft/server/ItemStack;III)V
        12: iconst_m1     
        13: istore        8
        15: goto          204
        18: iconst_m1     
        19: istore        9
        21: goto          195
        24: iconst_m1     
        25: istore        10
        27: goto          186
        30: iload         4
        32: getstatic     #52                 // Field net/minecraft/server/Block.REDSTONE_ORE:Lnet/minecraft/server/Block;
        35: getfield      #88                 // Field net/minecraft/server/Block.id:I
        38: if_icmpeq     103
        41: iload         4
        43: getstatic     #55                 // Field net/minecraft/server/Block.GLOWING_REDSTONE_ORE:Lnet/minecraft/server/Block;
        46: getfield      #88                 // Field net/minecraft/server/Block.id:I
        49: if_icmpeq     103
        52: aload_1       
        53: iload         5
        55: iload         8
        57: iadd          
        58: iload         6
        60: iload         9
        62: iadd          
        63: iload         7
        65: iload         10
        67: iadd          
        68: invokevirtual #183                // Method net/minecraft/server/World.getTypeId:(III)I
        71: iload         4
        73: if_icmpne     183
        76: aload_0       
        77: aload_1       
        78: aload_2       
        79: aload_3       
        80: iload         4
        82: iload         5
        84: iload         8
        86: iadd          
        87: iload         6
        89: iload         9
        91: iadd          
        92: iload         7
        94: iload         10
        96: iadd          
        97: invokevirtual #330                // Method doBreakS:(Lnet/minecraft/server/World;Lnet/minecraft/server/ItemStack;Lnet/minecraft/server/EntityHuman;IIII)V
       100: goto          183
       103: aload_1       
       104: iload         5
       106: iload         8
       108: iadd          
       109: iload         6
       111: iload         9
       113: iadd          
       114: iload         7
       116: iload         10
       118: iadd          
       119: invokevirtual #183                // Method net/minecraft/server/World.getTypeId:(III)I
       122: getstatic     #55                 // Field net/minecraft/server/Block.GLOWING_REDSTONE_ORE:Lnet/minecraft/server/Block;
       125: getfield      #88                 // Field net/minecraft/server/Block.id:I
       128: if_icmpeq     159
       131: aload_1       
       132: iload         5
       134: iload         8
       136: iadd          
       137: iload         6
       139: iload         9
       141: iadd          
       142: iload         7
       144: iload         10
       146: iadd          
       147: invokevirtual #183                // Method net/minecraft/server/World.getTypeId:(III)I
       150: getstatic     #52                 // Field net/minecraft/server/Block.REDSTONE_ORE:Lnet/minecraft/server/Block;
       153: getfield      #88                 // Field net/minecraft/server/Block.id:I
       156: if_icmpne     183
       159: aload_0       
       160: aload_1       
       161: aload_2       
       162: aload_3       
       163: iload         4
       165: iload         5
       167: iload         8
       169: iadd          
       170: iload         6
       172: iload         9
       174: iadd          
       175: iload         7
       177: iload         10
       179: iadd          
       180: invokevirtual #330                // Method doBreakS:(Lnet/minecraft/server/World;Lnet/minecraft/server/ItemStack;Lnet/minecraft/server/EntityHuman;IIII)V
       183: iinc          10, 1
       186: iload         10
       188: iconst_1      
       189: if_icmple     30
       192: iinc          9, 1
       195: iload         9
       197: iconst_1      
       198: if_icmple     24
       201: iinc          8, 1
       204: iload         8
       206: iconst_1      
       207: if_icmple     18
       210: aload_0       
       211: aload_1       
       212: aload_2       
       213: aload_3       
       214: invokestatic  #216                // Method ee/EEBase.playerX:(Lnet/minecraft/server/EntityHuman;)D
       217: aload_3       
       218: invokestatic  #219                // Method ee/EEBase.playerY:(Lnet/minecraft/server/EntityHuman;)D
       221: aload_3       
       222: invokestatic  #222                // Method ee/EEBase.playerZ:(Lnet/minecraft/server/EntityHuman;)D
       225: invokevirtual #202                // Method ejectDropList:(Lnet/minecraft/server/World;Lnet/minecraft/server/ItemStack;DDD)V
       228: return        
      LineNumberTable:
        line 347: 0
        line 349: 12
        line 351: 18
        line 353: 24
        line 355: 30
        line 357: 52
        line 359: 76
        line 362: 103
        line 364: 159
        line 353: 183
        line 351: 192
        line 349: 201
        line 370: 210
        line 371: 228
      LocalVariableTable:
        Start  Length  Slot  Name   Signature
               0     229     0  this   Lee/ItemRedPickaxe;
               0     229     1  var1   Lnet/minecraft/server/World;
               0     229     2  var2   Lnet/minecraft/server/ItemStack;
               0     229     3  var3   Lnet/minecraft/server/EntityHuman;
               0     229     4  var4   I
               0     229     5  var5   I
               0     229     6  var6   I
               0     229     7  var7   I
              15     195     8  var8   I
              21     180     9  var9   I
              27     165    10 var10   I
      StackMapTable: number_of_entries = 10
           frame_type = 252 /* append */
             offset_delta = 18
        locals = [ int ]
           frame_type = 252 /* append */
             offset_delta = 5
        locals = [ int ]
           frame_type = 252 /* append */
             offset_delta = 5
        locals = [ int ]
           frame_type = 251 /* same_frame_extended */
          offset_delta = 69
           frame_type = 2 /* same */
           frame_type = 55 /* same */
           frame_type = 23 /* same */
           frame_type = 2 /* same */
           frame_type = 250 /* chop */
          offset_delta = 8
           frame_type = 250 /* chop */
          offset_delta = 8


  public boolean canDestroySpecialBlock(net.minecraft.server.Block);
    flags: ACC_PUBLIC
    Code:
      stack=2, locals=2, args_size=2
         0: aload_1       
         1: getstatic     #70                 // Field net/minecraft/server/Block.OBSIDIAN:Lnet/minecraft/server/Block;
         4: if_acmpne     11
         7: iconst_1      
         8: goto          130
        11: aload_1       
        12: getstatic     #49                 // Field net/minecraft/server/Block.DIAMOND_BLOCK:Lnet/minecraft/server/Block;
        15: if_acmpeq     129
        18: aload_1       
        19: getstatic     #46                 // Field net/minecraft/server/Block.DIAMOND_ORE:Lnet/minecraft/server/Block;
        22: if_acmpeq     129
        25: aload_1       
        26: getstatic     #40                 // Field net/minecraft/server/Block.GOLD_BLOCK:Lnet/minecraft/server/Block;
        29: if_acmpeq     125
        32: aload_1       
        33: getstatic     #43                 // Field net/minecraft/server/Block.GOLD_ORE:Lnet/minecraft/server/Block;
        36: if_acmpeq     125
        39: aload_1       
        40: getstatic     #34                 // Field net/minecraft/server/Block.IRON_BLOCK:Lnet/minecraft/server/Block;
        43: if_acmpeq     121
        46: aload_1       
        47: getstatic     #31                 // Field net/minecraft/server/Block.IRON_ORE:Lnet/minecraft/server/Block;
        50: if_acmpeq     121
        53: aload_1       
        54: getstatic     #67                 // Field net/minecraft/server/Block.LAPIS_BLOCK:Lnet/minecraft/server/Block;
        57: if_acmpeq     117
        60: aload_1       
        61: getstatic     #64                 // Field net/minecraft/server/Block.LAPIS_ORE:Lnet/minecraft/server/Block;
        64: if_acmpeq     117
        67: aload_1       
        68: getstatic     #52                 // Field net/minecraft/server/Block.REDSTONE_ORE:Lnet/minecraft/server/Block;
        71: if_acmpeq     113
        74: aload_1       
        75: getstatic     #55                 // Field net/minecraft/server/Block.GLOWING_REDSTONE_ORE:Lnet/minecraft/server/Block;
        78: if_acmpeq     113
        81: aload_1       
        82: getfield      #107                // Field net/minecraft/server/Block.material:Lnet/minecraft/server/Material;
        85: getstatic     #111                // Field net/minecraft/server/Material.STONE:Lnet/minecraft/server/Material;
        88: if_acmpne     95
        91: iconst_1      
        92: goto          130
        95: aload_1       
        96: getfield      #107                // Field net/minecraft/server/Block.material:Lnet/minecraft/server/Material;
        99: getstatic     #115                // Field net/minecraft/server/Material.ORE:Lnet/minecraft/server/Material;
       102: if_acmpne     109
       105: iconst_1      
       106: goto          130
       109: iconst_0      
       110: goto          130
       113: iconst_1      
       114: goto          130
       117: iconst_1      
       118: goto          130
       121: iconst_1      
       122: goto          130
       125: iconst_1      
       126: goto          130
       129: iconst_1      
       130: ireturn       
      LineNumberTable:
        line 378: 0
      LocalVariableTable:
        Start  Length  Slot  Name   Signature
               0     131     0  this   Lee/ItemRedPickaxe;
               0     131     1  var1   Lnet/minecraft/server/Block;
      StackMapTable: number_of_entries = 14
           frame_type = 11 /* same */
           frame_type = 251 /* same_frame_extended */
          offset_delta = 83
           frame_type = 13 /* same */
           frame_type = 64 /* same_locals_1_stack_item */
          stack = [ int ]
           frame_type = 2 /* same */
           frame_type = 64 /* same_locals_1_stack_item */
          stack = [ int ]
           frame_type = 2 /* same */
           frame_type = 64 /* same_locals_1_stack_item */
          stack = [ int ]
           frame_type = 2 /* same */
           frame_type = 64 /* same_locals_1_stack_item */
          stack = [ int ]
           frame_type = 2 /* same */
           frame_type = 64 /* same_locals_1_stack_item */
          stack = [ int ]
           frame_type = 2 /* same */
           frame_type = 64 /* same_locals_1_stack_item */
          stack = [ int ]


  public void doRelease(net.minecraft.server.ItemStack, net.minecraft.server.World, net.minecraft.server.EntityHuman);
    flags: ACC_PUBLIC
    Code:
      stack=4, locals=4, args_size=4
         0: aload_0       
         1: aload_1       
         2: aload_2       
         3: aload_3       
         4: invokevirtual #312                // Method doBreak:(Lnet/minecraft/server/ItemStack;Lnet/minecraft/server/World;Lnet/minecraft/server/EntityHuman;)V
         7: return        
      LineNumberTable:
        line 383: 0
        line 384: 7
      LocalVariableTable:
        Start  Length  Slot  Name   Signature
               0       8     0  this   Lee/ItemRedPickaxe;
               0       8     1  var1   Lnet/minecraft/server/ItemStack;
               0       8     2  var2   Lnet/minecraft/server/World;
               0       8     3  var3   Lnet/minecraft/server/EntityHuman;

  public void doAlternate(net.minecraft.server.ItemStack, net.minecraft.server.World, net.minecraft.server.EntityHuman);
    flags: ACC_PUBLIC
    Code:
      stack=1, locals=4, args_size=4
         0: aload_3       
         1: invokestatic  #337                // Method ee/EEBase.updateToolMode:(Lnet/minecraft/server/EntityHuman;)V
         4: return        
      LineNumberTable:
        line 388: 0
        line 389: 4
      LocalVariableTable:
        Start  Length  Slot  Name   Signature
               0       5     0  this   Lee/ItemRedPickaxe;
               0       5     1  var1   Lnet/minecraft/server/ItemStack;
               0       5     2  var2   Lnet/minecraft/server/World;
               0       5     3  var3   Lnet/minecraft/server/EntityHuman;

  public void doToggle(net.minecraft.server.ItemStack, net.minecraft.server.World, net.minecraft.server.EntityHuman);
    flags: ACC_PUBLIC
    Code:
      stack=0, locals=4, args_size=4
         0: return        
      LineNumberTable:
        line 391: 0
      LocalVariableTable:
        Start  Length  Slot  Name   Signature
               0       1     0  this   Lee/ItemRedPickaxe;
               0       1     1  var1   Lnet/minecraft/server/ItemStack;
               0       1     2  var2   Lnet/minecraft/server/World;
               0       1     3  var3   Lnet/minecraft/server/EntityHuman;
}
